[
  {
    "id": "1",
    "title": "Tren entre Montañas",
    "subtitle": "3D / Blender / Animación",
    "subtitle_en": "3D / Blender / Animation",
    "desc": "Todos los assets generados proceduralmente",
    "desc_en": "",
    "stack": ["Blender", "Cycles", "Modifiers", "Premier"],
    "captions": {}
  },
  {
    "id": "2",
    "title": "Tren Montañas",
    "subtitle": "Animación / Shaders",
    "subtitle_en": "Animation / Shaders",
    "desc": "Animación de entorno natural con énfasis en la escala y la atmósfera.",
    "desc_en": "Natural environment animation emphasizing scale and atmosphere.",
    "stack": ["Blender", "Evee"],
    "captions": {}
  },
  {
    "id": "3",
    "title": "Voronoi Flux",
    "subtitle": "Motion Graphics",
    "subtitle_en": "Motion Graphics",
    "desc": "Exploración de caos organizado.",
    "desc_en": "Exploration of organized chaos.",
    "stack": ["After Effects", "Simulation"],
    "captions": {}
  },
  {
    "id": "4",
    "title": "Walk Cycle",
    "subtitle": "Visuals",
    "subtitle_en": "Visuals",
    "desc": "Pruebas de rigging y animación.",
    "desc_en": "Rigging and animation tests.",
    "stack": ["Blender", "Mixamo"],
    "captions": {}
  },
  {
    "id": "5",
    "title": "Dibujos",
    "subtitle": "Ilustración / 2D",
    "subtitle_en": "Illustration / 2D",
    "desc": "Estudio de carácter y movimiento a través de la ilustración.",
    "desc_en": "Character and movement study through illustration.",
    "stack": ["Photoshop", "Procreate"],
    "captions": {
      "0": "",
      "1": "",
      "2": ""
    }
  },
  {
    "id": "6",
    "title": "Procedural Span",
    "subtitle": "Geometry Nodes",
    "subtitle_en": "Geometry Nodes",
    "desc": "Arquitectura generada por nodos.",
    "desc_en": "Node-based generative architecture.",
    "stack": ["Blender", "GeoNodes"],
    "captions": {}
  },
  {
    "id": "7",
    "title": "Nombre Proyecto 7",
    "subtitle": "Categoría / Rol",
    "subtitle_en": "Category / Role",
    "desc": "Descripción breve del proyecto 7 en español.",
    "desc_en": "Brief description of project 7 in English.",
    "stack": ["Herramienta 1", "Herramienta 2"],
    "captions": {
      "v0": "",
      "0": ""
    }
  },
  {
    "id": "8",
    "title": "",
    "subtitle": "",
    "subtitle_en": "",
    "desc": "",
    "desc_en": "",
    "stack": ["Herramienta A", "Herramienta B"],
    "captions": {}
  }
]
